cjtool/__init__.py
cjtool/addconsole.py
cjtool/cdbtool.py
cjtool/common.py
cjtool/debuger.py
cjtool/indent.py
cjtool/monitor.py
cjtool/search.py
cjtool/stl.py
cjtool/stringtool.py
cjtool/gfy/__init__.py
cjtool/gfy/edoinfo.py
cjtool/gfy/print.py
cjtool/gfy/printedo.py
cjtool-0.29.10.dist-info/METADATA
cjtool-0.29.10.dist-info/WHEEL
cjtool-0.29.10.dist-info/entry_points.txt
cjtool-0.29.10.dist-info/top_level.txt
cjtool-0.29.10.dist-info/RECORD
