Metadata-Version: 2.1
Name: cjtool
Version: 0.29.10
Summary: Provide some tools in C++ development
Author-email: Jun Chen <junc76@gmail.com>
Requires-Python: >=3.9
Requires-Dist: colorama
Requires-Dist: pyperclip
Requires-Dist: pexpect
Requires-Dist: pykd
Requires-Dist: PyYAML
Requires-Dist: sourceline
